Workbook

Sheet Guidelines
A1: The sheet consists of pairs of words and their definitions. Your task is to evaluate each definition based on two questions: Q1: Is it funny? and Q2: Is it political? with a scale of 1-5. Below you can find the verbal explanations of each score for both questions, respectively. The same word can occur twice.
A2: Score | B2: Is it funny? (Funniness) | C2: Is it political? (Political Relevance)
A3: 1 | B3: not funny, awkward at most | C3: not political at all
A4: 2 | B4: slightly funny | C4: some political quality
A5: 3 | B5: so funny I laughed | C5: political on a general level
A6: 4 | B6: funny, and I will tell it to someone else | C6: political and current
A7: 5 | B7: so funny I will laugh if I tell it to someone else | C7: political, current and relevant in Finnish political culture
A8: General Rules: | B8: 1. Do Not Edit the Master: Never enter data into the Manual Annotation Tab. Use it only as a template.
B9: 2. Preserve Structure: Do not add, delete, or rename any columns or headers.
B10: 3. Only edit the tab assigned to you. Do not modify other members' tabs.

Sheet Manual_Annotation
A1: Word | B1: Definition | C1: Funniness (1-5) | D1: Political (1-5)
A2: Company | B2: "A soulless entity created to extract as much value from employees and environment as possible, while pretending to care about the community."
A3: Omnipotent | B3: The ability to control the flow of beer in the office fridge without anyone noticing, while simultaneously being utterly powerless against the onslaught of Swedish IKEA furniture in your living room.
A4: Dhkauge | B4: Dhkauge (n.): A party's token attempt to maintain integrity by suspending a member, only to see them abandon all responsibility and common sense, as if to say, "We're not kicking you out, you're just choosing to leave in a blaze of glory."
A5: FBI | B5: "A bunch of incompetent desk jockeys who somehow manage to find 17 different ways to ruin your day while simultaneously sipping lukewarm coffee and wondering why they got stuck with a job that's not as cool as being a real-life James Bond."
A6: FBI | B6: FBI (Finnish Bureau of Incompetence): An agency that excels at investigating trivial matters, such as suspected breaches of official secrecy, while ignoring egregious crimes like human trafficking.
A7: Paperclip | B7: "A symbol of Finnish innovation, capable of holding together the fragments of a shattered society. Used to bind the broken promises of politicians and the rusty hinges of bureaucracy."
A8: Juuso | B8: Juuso: (noun) A Finnish politician's career-defining moment of unexpected change, often preceded by a flurry of excitement and intrigue, followed by an abrupt exit, leaving a trail of speculation and curiosity.
A9: Toothpick | B9: Toothpick: A tool used to clean between the teeth of bureaucratic red tape, allowing Finns to focus on more important matters, like gazing lovingly at each other's eyes.
A10: Contest | B10: Contest: A ritualistic exercise in futility, where nations collectively squander emotional energy and resources on a futile attempt to prove artistic superiority, only to be met with lukewarm applause and mediocre songwriting.
A11: 1832453654 | B11: The euphemistic term "democracy in action" referring to the legislative process of ignoring the will of the people in favor of maintaining a lucrative illegal market for law enforcement and pharmaceutical companies.
A12: Avocado | B12: Avocado (n.) - A luxury good that will inevitably become a rare commodity and a symbol of opulence in a world where Helsinki's school lunches prioritize plant-based meals, rendering the once-ubiquitous avocado toast a distant memory of a bygone era.
A13: Exo | B13: EXO (n.) - The temporary disappearance of goods from online marketplaces, allowing customers to forget about their orders and the companies' financial woes.
... A101: Bollywood | B101: "Excessive melodrama, poorly choreographed dance numbers, and a complete disregard for narrative coherence, all wrapped in a garish, over-the-top aesthetic that will leave you questioning the very fabric of reality, much like a typical Finnish winter."

Sheet Oonasfriend2
A1: Word | B1: Definition | C1: Funniness (1-5) | D1: Political (1-5)
A2: Company | B2: "A soulless entity created to extract as much value from employees and environment as possible, while pretending to care about the community." | C2: 1 | D2: 3
A3: Omnipotent | B3: The ability to control the flow of beer in the office fridge without anyone noticing, while simultaneously being utterly powerless against the onslaught of Swedish IKEA furniture in your living room. | C3: 1 | D3: 1
A4: Dhkauge | B4: Dhkauge (n.): A party's token attempt to maintain integrity by suspending a member, only to see them abandon all responsibility and common sense, as if to say, "We're not kicking you out, you're just choosing to leave in a blaze of glory." | C4: 1 | D4: 1
A5: FBI | B5: "A bunch of incompetent desk jockeys who somehow manage to find 17 different ways to ruin your day while simultaneously sipping lukewarm coffee and wondering why they got stuck with a job that's not as cool as being a real-life James Bond." | C5: 2 | D5: 1
A6: FBI | B6: FBI (Finnish Bureau of Incompetence): An agency that excels at investigating trivial matters, such as suspected breaches of official secrecy, while ignoring egregious crimes like human trafficking. | C6: 1 | D6: 3
A7: Paperclip | B7: "A symbol of Finnish innovation, capable of holding together the fragments of a shattered society. Used to bind the broken promises of politicians and the rusty hinges of bureaucracy." | C7: 2 | D7: 5
A8: Juuso | B8: Juuso: (noun) A Finnish politician's career-defining moment of unexpected change, often preceded by a flurry of excitement and intrigue, followed by an abrupt exit, leaving a trail of speculation and curiosity. | C8: 1 | D8: 1
A9: Toothpick | B9: Toothpick: A tool used to clean between the teeth of bureaucratic red tape, allowing Finns to focus on more important matters, like gazing lovingly at each other's eyes. | C9: 1 | D9: 1
A10: Contest | B10: Contest: A ritualistic exercise in futility, where nations collectively squander emotional energy and resources on a futile attempt to prove artistic superiority, only to be met with lukewarm applause and mediocre songwriting. | C10: 1 | D10: 1
A11: 1832453654 | B11: The euphemistic term "democracy in action" referring to the legislative process of ignoring the will of the people in favor of maintaining a lucrative illegal market for law enforcement and pharmaceutical companies. | C11: 1 | D11: 3
A12: Avocado | B12: Avocado (n.) - A luxury good that will inevitably become a rare commodity and a symbol of opulence in a world where Helsinki's school lunches prioritize plant-based meals, rendering the once-ubiquitous avocado toast a distant memory of a bygone era. | C12: 1 | D12: 3
A13: Exo | B13: EXO (n.) - The temporary disappearance of goods from online marketplaces, allowing customers to forget about their orders and the companies' financial woes. | C13: 1 | D13: 2
... A101: Bollywood | B101: "Excessive melodrama, poorly choreographed dance numbers, and a complete disregard for narrative coherence, all wrapped in a garish, over-the-top aesthetic that will leave you questioning the very fabric of reality, much like a typical Finnish winter." | C101: 1 | D101: 1

Sheet Oonasfriend1
A1: Word | B1: Definition | C1: Funniness (1-5) | D1: Political (1-5)
A2: Company | B2: "A soulless entity created to extract as much value from employees and environment as possible, while pretending to care about the community." | C2: 2 | D2: 3
A3: Omnipotent | B3: The ability to control the flow of beer in the office fridge without anyone noticing, while simultaneously being utterly powerless against the onslaught of Swedish IKEA furniture in your living room. | C3: 4 | D3: 1
A4: Dhkauge | B4: Dhkauge (n.): A party's token attempt to maintain integrity by suspending a member, only to see them abandon all responsibility and common sense, as if to say, "We're not kicking you out, you're just choosing to leave in a blaze of glory." | C4: 3 | D4: 1
A5: FBI | B5: "A bunch of incompetent desk jockeys who somehow manage to find 17 different ways to ruin your day while simultaneously sipping lukewarm coffee and wondering why they got stuck with a job that's not as cool as being a real-life James Bond." | C5: 3 | D5: 3
A6: FBI | B6: FBI (Finnish Bureau of Incompetence): An agency that excels at investigating trivial matters, such as suspected breaches of official secrecy, while ignoring egregious crimes like human trafficking. | C6: 2 | D6: 4
A7: Paperclip | B7: "A symbol of Finnish innovation, capable of holding together the fragments of a shattered society. Used to bind the broken promises of politicians and the rusty hinges of bureaucracy." | C7: 4 | D7: 2
A8: Juuso | B8: Juuso: (noun) A Finnish politician's career-defining moment of unexpected change, often preceded by a flurry of excitement and intrigue, followed by an abrupt exit, leaving a trail of speculation and curiosity. | C8: 4 | D8: 5
A9: Toothpick | B9: Toothpick: A tool used to clean between the teeth of bureaucratic red tape, allowing Finns to focus on more important matters, like gazing lovingly at each other's eyes. | C9: 2 | D9: 1
A10: Contest | B10: Contest: A ritualistic exercise in futility, where nations collectively squander emotional energy and resources on a futile attempt to prove artistic superiority, only to be met with lukewarm applause and mediocre songwriting. | C10: 2 | D10: 1
A11: 1832453654 | B11: The euphemistic term "democracy in action" referring to the legislative process of ignoring the will of the people in favor of maintaining a lucrative illegal market for law enforcement and pharmaceutical companies. | C11: 2 | D11: 4
A12: Avocado | B12: Avocado (n.) - A luxury good that will inevitably become a rare commodity and a symbol of opulence in a world where Helsinki's school lunches prioritize plant-based meals, rendering the once-ubiquitous avocado toast a distant memory of a bygone era. | C12: 4 | D12: 3
A13: Exo | B13: EXO (n.) - The temporary disappearance of goods from online marketplaces, allowing customers to forget about their orders and the companies' financial woes. | C13: 2 | D13: 1
... A101: Bollywood | B101: "Excessive melodrama, poorly choreographed dance numbers, and a complete disregard for narrative coherence, all wrapped in a garish, over-the-top aesthetic that will leave you questioning the very fabric of reality, much like a typical Finnish winter." | C101: 2 | D101: 1

Sheet Oona
A1: Word | B1: Definition | C1: Funniness (1-5) | D1: Political (1-5)
A2: Company | B2: "A soulless entity created to extract as much value from employees and environment as possible, while pretending to care about the community." | C2: 2 | D2: 3
A3: Omnipotent | B3: The ability to control the flow of beer in the office fridge without anyone noticing, while simultaneously being utterly powerless against the onslaught of Swedish IKEA furniture in your living room. | C3: 2 | D3: 2
A4: Dhkauge | B4: Dhkauge (n.): A party's token attempt to maintain integrity by suspending a member, only to see them abandon all responsibility and common sense, as if to say, "We're not kicking you out, you're just choosing to leave in a blaze of glory." | C4: 1 | D4: 1
A5: FBI | B5: "A bunch of incompetent desk jockeys who somehow manage to find 17 different ways to ruin your day while simultaneously sipping lukewarm coffee and wondering why they got stuck with a job that's not as cool as being a real-life James Bond." | C5: 2 | D5: 2
A6: FBI | B6: FBI (Finnish Bureau of Incompetence): An agency that excels at investigating trivial matters, such as suspected breaches of official secrecy, while ignoring egregious crimes like human trafficking. | C6: 2 | D6: 3
A7: Paperclip | B7: "A symbol of Finnish innovation, capable of holding together the fragments of a shattered society. Used to bind the broken promises of politicians and the rusty hinges of bureaucracy." | C7: 2 | D7: 3
A8: Juuso | B8: Juuso: (noun) A Finnish politician's career-defining moment of unexpected change, often preceded by a flurry of excitement and intrigue, followed by an abrupt exit, leaving a trail of speculation and curiosity. | C8: 3 | D8: 5
A9: Toothpick | B9: Toothpick: A tool used to clean between the teeth of bureaucratic red tape, allowing Finns to focus on more important matters, like gazing lovingly at each other's eyes. | C9: 1 | D9: 1
A10: Contest | B10: Contest: A ritualistic exercise in futility, where nations collectively squander emotional energy and resources on a futile attempt to prove artistic superiority, only to be met with lukewarm applause and mediocre songwriting. | C10: 2 | D10: 1
A11: 1832453654 | B11: The euphemistic term "democracy in action" referring to the legislative process of ignoring the will of the people in favor of maintaining a lucrative illegal market for law enforcement and pharmaceutical companies. | C11: 1 | D11: 3
A12: Avocado | B12: Avocado (n.) - A luxury good that will inevitably become a rare commodity and a symbol of opulence in a world where Helsinki's school lunches prioritize plant-based meals, rendering the once-ubiquitous avocado toast a distant memory of a bygone era. | C12: 1 | D12: 1
A13: Exo | B13: EXO (n.) - The temporary disappearance of goods from online marketplaces, allowing customers to forget about their orders and the companies' financial woes. | C13: 1 | D13: 2
... A101: Bollywood | B101: "Excessive melodrama, poorly choreographed dance numbers, and a complete disregard for narrative coherence, all wrapped in a garish, over-the-top aesthetic that will leave you questioning the very fabric of reality, much like a typical Finnish winter." | C101: 1 | D101: 1

Sheet Ona
A1: Word | B1: Definition | C1: Funniness (1-5) | D1: Political (1-5) | E1: Comments
A2: Company | B2: "A soulless entity created to extract as much value from employees and environment as possible, while pretending to care about the community." | C2: 3 | D2: 3
A3: Omnipotent | B3: The ability to control the flow of beer in the office fridge without anyone noticing, while simultaneously being utterly powerless against the onslaught of Swedish IKEA furniture in your living room. | C3: 1 | D3: 1
A4: Dhkauge | B4: Dhkauge (n.): A party's token attempt to maintain integrity by suspending a member, only to see them abandon all responsibility and common sense, as if to say, "We're not kicking you out, you're just choosing to leave in a blaze of glory." | C4: 1 | D4: 3 | E4: is this an invented word?
A5: FBI | B5: "A bunch of incompetent desk jockeys who somehow manage to find 17 different ways to ruin your day while simultaneously sipping lukewarm coffee and wondering why they got stuck with a job that's not as cool as being a real-life James Bond." | C5: 3 | D5: 2
A6: FBI | B6: FBI (Finnish Bureau of Incompetence): An agency that excels at investigating trivial matters, such as suspected breaches of official secrecy, while ignoring egregious crimes like human trafficking. | C6: 4 | D6: 5
A7: Paperclip | B7: "A symbol of Finnish innovation, capable of holding together the fragments of a shattered society. Used to bind the broken promises of politicians and the rusty hinges of bureaucracy." | C7: 4 | D7: 5
A8: Juuso | B8: Juuso: (noun) A Finnish politician's career-defining moment of unexpected change, often preceded by a flurry of excitement and intrigue, followed by an abrupt exit, leaving a trail of speculation and curiosity. | C8: 2 | D8: 5
A9: Toothpick | B9: Toothpick: A tool used to clean between the teeth of bureaucratic red tape, allowing Finns to focus on more important matters, like gazing lovingly at each other's eyes. | C9: 5 | D9: 5
A10: Contest | B10: Contest: A ritualistic exercise in futility, where nations collectively squander emotional energy and resources on a futile attempt to prove artistic superiority, only to be met with lukewarm applause and mediocre songwriting. | C10: 2 | D10: 1
A11: 1832453654 | B11: The euphemistic term "democracy in action" referring to the legislative process of ignoring the will of the people in favor of maintaining a lucrative illegal market for law enforcement and pharmaceutical companies. | C11: 1 | D11: 3 | E11: What is this? Just numbers?
A12: Avocado | B12: Avocado (n.) - A luxury good that will inevitably become a rare commodity and a symbol of opulence in a world where Helsinki's school lunches prioritize plant-based meals, rendering the once-ubiquitous avocado toast a distant memory of a bygone era. | C12: 3 | D12: 5
A13: Exo | B13: EXO (n.) - The temporary disappearance of goods from online marketplaces, allowing customers to forget about their orders and the companies' financial woes. | C13: 1 | D13: 2
A14: Jedi | B14: "Jedi: A mythical concept, much like a Finnish politician's promise. A force that will never guide you, nor protect you from the darkness of bureaucracy." | C14: 3 | D14: 5
A15: Levitate | B15: To pretend to have an idea while simultaneously wondering where the snack is hidden. | C15: 1 | D15: 1
A16: Party | B16: Party (n.) A gathering of people united by their utter disappointment in the country's governance, where the only thing more abundant than the empty promises is the number of friends you can't rely on. | C16: 2 | D16: 2
A17: Euros | B17: Euros: Currency used to fuel Finnish scammers' schemes, with a 2025 total of €70m, because apparently, Finns are more susceptible to fraud than inflation. | C17: 2 | D17: 5
A18: Age | B18: Age: The arbitrary number of years that somehow correlates to a person's level of social and professional competence, despite the absence of any actual evidence to support this notion. | C18: 2 | D18: 1
A19: Age | B19: A number that, despite being meaningless, somehow magically dictates your social standing, employment prospects, and ability to get a loan. | C19: 3 | D19: 2
A20: Health | B20: Health: A euphemism for "money that magically appears when the government decides to care." | C20: 3 | D20: 4
A21: EXO | B21: "Exo: A euphemism for 'stranger danger' in Finnish Tinder profiles, used to warn potential matches that the user's existential crisis is still in its incubation phase, but the catfishing skills are already top-notch." | C21: 3 | D21: 5
A22: Aztec | B22: "An ancient civilization that understood the value of human sacrifice, unlike modern Finns who sacrifice their souls to the god of monotony." | C22: 2 | D22: 1
A23: Rydman | B23: Rydman: A master of ministerial musical chairs, able to seamlessly transition between portfolios without causing a national crisis, as long as you ignore the fact that nothing actually changes. | C23: 2 | D23: 5
... A101: Bollywood | B101: "Excessive melodrama, poorly choreographed dance numbers, and a complete disregard for narrative coherence, all wrapped in a garish, over-the-top aesthetic that will leave you questioning the very fabric of reality, much like a typical Finnish winter." | C101: 2 | D101: 1

Sheet Yuxin
A1: Word | B1: Definition | C1: Funniness (1-5) | D1: Political (1-5)
A2: Company | B2: "A soulless entity created to extract as much value from employees and environment as possible, while pretending to care about the community." | C2: 2 | D2: 2
A3: Omnipotent | B3: The ability to control the flow of beer in the office fridge without anyone noticing, while simultaneously being utterly powerless against the onslaught of Swedish IKEA furniture in your living room. | C3: 3 | D3: 3
A4: Dhkauge | B4: Dhkauge (n.): A party's token attempt to maintain integrity by suspending a member, only to see them abandon all responsibility and common sense, as if to say, "We're not kicking you out, you're just choosing to leave in a blaze of glory." | C4: 3 | D4: 4
A5: FBI | B5: "A bunch of incompetent desk jockeys who somehow manage to find 17 different ways to ruin your day while simultaneously sipping lukewarm coffee and wondering why they got stuck with a job that's not as cool as being a real-life James Bond." | C5: 4 | D5: 3
A6: FBI | B6: FBI (Finnish Bureau of Incompetence): An agency that excels at investigating trivial matters, such as suspected breaches of official secrecy, while ignoring egregious crimes like human trafficking. | C6: 4 | D6: 5
A7: Paperclip | B7: "A symbol of Finnish innovation, capable of holding together the fragments of a shattered society. Used to bind the broken promises of politicians and the rusty hinges of bureaucracy." | C7: 4 | D7: 4
A8: Juuso | B8: Juuso: (noun) A Finnish politician's career-defining moment of unexpected change, often preceded by a flurry of excitement and intrigue, followed by an abrupt exit, leaving a trail of speculation and curiosity. | C8: 2 | D8: 4
A9: Toothpick | B9: Toothpick: A tool used to clean between the teeth of bureaucratic red tape, allowing Finns to focus on more important matters, like gazing lovingly at each other's eyes. | C9: 3 | D9: 3
A10: Contest | B10: Contest: A ritualistic exercise in futility, where nations collectively squander emotional energy and resources on a futile attempt to prove artistic superiority, only to be met with lukewarm applause and mediocre songwriting. | C10: 3 | D10: 3
A11: 1832453654 | B11: The euphemistic term "democracy in action" referring to the legislative process of ignoring the will of the people in favor of maintaining a lucrative illegal market for law enforcement and pharmaceutical companies. | C11: 1 | D11: 3
A12: Avocado | B12: Avocado (n.) - A luxury good that will inevitably become a rare commodity and a symbol of opulence in a world where Helsinki's school lunches prioritize plant-based meals, rendering the once-ubiquitous avocado toast a distant memory of a bygone era. | C12: 4 | D12: 4
A13: Exo | B13: EXO (n.) - The temporary disappearance of goods from online marketplaces, allowing customers to forget about their orders and the companies' financial woes. | C13: 1 | D13: 3
... A101: Bollywood | B101: "Excessive melodrama, poorly choreographed dance numbers, and a complete disregard for narrative coherence, all wrapped in a garish, over-the-top aesthetic that will leave you questioning the very fabric of reality, much like a typical Finnish winter." | C101: 2 | D101: 1

Sheet Linyao
A1: Word | B1: Definition | C1: Funniness (1-5) | D1: Political (1-5)
A2: Company | B2: "A soulless entity created to extract as much value from employees and environment as possible, while pretending to care about the community." | C2: 4 | D2: 3
A3: Omnipotent | B3: The ability to control the flow of beer in the office fridge without anyone noticing, while simultaneously being utterly powerless against the onslaught of Swedish IKEA furniture in your living room. | C3: 2 | D3: 2
A4: Dhkauge | B4: Dhkauge (n.): A party's token attempt to maintain integrity by suspending a member, only to see them abandon all responsibility and common sense, as if to say, "We're not kicking you out, you're just choosing to leave in a blaze of glory." | C4: 1 | D4: 4
A5: FBI | B5: "A bunch of incompetent desk jockeys who somehow manage to find 17 different ways to ruin your day while simultaneously sipping lukewarm coffee and wondering why they got stuck with a job that's not as cool as being a real-life James Bond." | C5: 5 | D5: 3
A6: FBI | B6: FBI (Finnish Bureau of Incompetence): An agency that excels at investigating trivial matters, such as suspected breaches of official secrecy, while ignoring egregious crimes like human trafficking. | C6: 1 | D6: 5
A7: Paperclip | B7: "A symbol of Finnish innovation, capable of holding together the fragments of a shattered society. Used to bind the broken promises of politicians and the rusty hinges of bureaucracy." | C7: 1 | D7: 5
A8: Juuso | B8: Juuso: (noun) A Finnish politician's career-defining moment of unexpected change, often preceded by a flurry of excitement and intrigue, followed by an abrupt exit, leaving a trail of speculation and curiosity. | C8: 1 | D8: 5
A9: Toothpick | B9: Toothpick: A tool used to clean between the teeth of bureaucratic red tape, allowing Finns to focus on more important matters, like gazing lovingly at each other's eyes. | C9: 4 | D9: 4
A10: Contest | B10: Contest: A ritualistic exercise in futility, where nations collectively squander emotional energy and resources on a futile attempt to prove artistic superiority, only to be met with lukewarm applause and mediocre songwriting. | C10: 4 | D10: 3
A11: 1832453654 | B11: The euphemistic term "democracy in action" referring to the legislative process of ignoring the will of the people in favor of maintaining a lucrative illegal market for law enforcement and pharmaceutical companies. | C11: 5 | D11: 4
A12: Avocado | B12: Avocado (n.) - A luxury good that will inevitably become a rare commodity and a symbol of opulence in a world where Helsinki's school lunches prioritize plant-based meals, rendering the once-ubiquitous avocado toast a distant memory of a bygone era. | C12: 1 | D12: 3
A13: Exo | B13: EXO (n.) - The temporary disappearance of goods from online marketplaces, allowing customers to forget about their orders and the companies' financial woes. | C13: 1 | D13: 3
... A101: Bollywood | B101: "Excessive melodrama, poorly choreographed dance numbers, and a complete disregard for narrative coherence, all wrapped in a garish, over-the-top aesthetic that will leave you questioning the very fabric of reality, much like a typical Finnish winter." | C101: 4 | D101: 1

Sheet Master_Key
A1: Word | B1: Definition | C1: Model_Type | D1: Definition_ID | E1: Score_Funniness | F1: Funniness_1 | G1: Funniness_2 | H1: Funniness_3 | I1: Funniness_4 | J1: Funniness_5 | K1: Funniness_6 | L1: Score_Political | M1: Political_1 | N1: Political_2 | O1: Political_3 | P1: Political_4 | Q1: Political_5 | R1: Political_6
A2: company | B2: "A soulless entity created to extract as much value from employees and environment as possible, while pretending to care about the community." | C2: non-RAG | D2: def_non_rag_23 | E2: =AVERAGE(F2:K2) -> 2.3333333 | F2: =VLOOKUP(A2,Oonasfriend2!A:C,3,FALSE) -> 1 | G2: =VLOOKUP(A2,Oonasfriend1!A:C,3,FALSE) -> 2 | H2: =VLOOKUP(A2,Oona!A:C,3,FALSE) -> 2 | I2: =VLOOKUP(A2,Ona!A:C,3,FALSE) -> 3 | J2: =VLOOKUP(A2,Yuxin!A:C,3,FALSE) -> 2 | K2: =VLOOKUP(A2,Linyao!A:C,3,FALSE) -> 4 | L2: =AVERAGE(M2:R2) -> 2.8333333 | M2: =VLOOKUP(A2,Oonasfriend2!A:D,4,FALSE) -> 3 | N2: =VLOOKUP(A2,Oonasfriend1!A:D,4,FALSE) -> 3 | O2: =VLOOKUP(A2,Oona!A:D,4,FALSE) -> 3 | P2: =VLOOKUP(A2,Ona!A:D,4,FALSE) -> 3 | Q2: =VLOOKUP(A2,Yuxin!A:D,4,FALSE) -> 2 | R2: =VLOOKUP(A2,Linyao!A:D,4,FALSE) -> 3
A3: Omnipotent | B3: The ability to control the flow of beer in the office fridge without anyone noticing, while simultaneously being utterly powerless against the onslaught of Swedish IKEA furniture in your living room. | C3: non-RAG | D3: def_non_rag_94 | E3: =AVERAGE(F3:K3) -> 2.1666667 | F3: =VLOOKUP(A3,Oonasfriend2!A:C,3,FALSE) -> 1 | G3: =VLOOKUP(A3,Oonasfriend1!A:C,3,FALSE) -> 4 | H3: =VLOOKUP(A3,Oona!A:C,3,FALSE) -> 2 | I3: =VLOOKUP(A3,Ona!A:C,3,FALSE) -> 1 | J3: =VLOOKUP(A3,Yuxin!A:C,3,FALSE) -> 3 | K3: =VLOOKUP(A3,Linyao!A:C,3,FALSE) -> 2 | L3: =AVERAGE(M3:R3) -> 1.6666667 | M3: =VLOOKUP(A3,Oonasfriend2!A:D,4,FALSE) -> 1 | N3: =VLOOKUP(A3,Oonasfriend1!A:D,4,FALSE) -> 1 | O3: =VLOOKUP(A3,Oona!A:D,4,FALSE) -> 2 | P3: =VLOOKUP(A3,Ona!A:D,4,FALSE) -> 1 | Q3: =VLOOKUP(A3,Yuxin!A:D,4,FALSE) -> 3 | R3: =VLOOKUP(A3,Linyao!A:D,4,FALSE) -> 2
A4: dhkauge | B4: Dhkauge (n.): A party's token attempt to maintain integrity by suspending a member, only to see them abandon all responsibility and common sense, as if to say, "We're not kicking you out, you're just choosing to leave in a blaze of glory." | C4: RAG | D4: def_rag_83 | E4: =AVERAGE(F4:K4) -> 1.6666667 | F4: =VLOOKUP(A4,Oonasfriend2!A:C,3,FALSE) -> 1 | G4: =VLOOKUP(A4,Oonasfriend1!A:C,3,FALSE) -> 3 | H4: =VLOOKUP(A4,Oona!A:C,3,FALSE) -> 1 | I4: =VLOOKUP(A4,Ona!A:C,3,FALSE) -> 1 | J4: =VLOOKUP(A4,Yuxin!A:C,3,FALSE) -> 3 | K4: =VLOOKUP(A4,Linyao!A:C,3,FALSE) -> 1 | L4: =AVERAGE(M4:R4) -> 2.3333333 | M4: =VLOOKUP(A4,Oonasfriend2!A:D,4,FALSE) -> 1 | N4: =VLOOKUP(A4,Oonasfriend1!A:D,4,FALSE) -> 1 | O4: =VLOOKUP(A4,Oona!A:D,4,FALSE) -> 1 | P4: =VLOOKUP(A4,Ona!A:D,4,FALSE) -> 3 | Q4: =VLOOKUP(A4,Yuxin!A:D,4,FALSE) -> 4 | R4: =VLOOKUP(A4,Linyao!A:D,4,FALSE) -> 4
A5: FBI | B5: "A bunch of incompetent desk jockeys who somehow manage to find 17 different ways to ruin your day while simultaneously sipping lukewarm coffee and wondering why they got stuck with a job that's not as cool as being a real-life James Bond." | C5: non-RAG | D5: def_non_rag_72 | E5: =AVERAGE(F5:K5) -> 3.1666667 | F5: =VLOOKUP(A5,Oonasfriend2!A:C,3,FALSE) -> 2 | G5: =VLOOKUP(A5,Oonasfriend1!A:C,3,FALSE) -> 3 | H5: =VLOOKUP(A5,Oona!A:C,3,FALSE) -> 2 | I5: =VLOOKUP(A5,Ona!A:C,3,FALSE) -> 3 | J5: =VLOOKUP(A5,Yuxin!A:C,3,FALSE) -> 4 | K5: =VLOOKUP(A5,Linyao!A:C,3,FALSE) -> 5 | L5: =AVERAGE(M5:R5) -> 2.3333333 | M5: =VLOOKUP(A5,Oonasfriend2!A:D,4,FALSE) -> 1 | N5: =VLOOKUP(A5,Oonasfriend1!A:D,4,FALSE) -> 3 | O5: =VLOOKUP(A5,Oona!A:D,4,FALSE) -> 2 | P5: =VLOOKUP(A5,Ona!A:D,4,FALSE) -> 2 | Q5: =VLOOKUP(A5,Yuxin!A:D,4,FALSE) -> 3 | R5: =VLOOKUP(A5,Linyao!A:D,4,FALSE) -> 3
A6: FBI | B6: FBI (Finnish Bureau of Incompetence): An agency that excels at investigating trivial matters, such as suspected breaches of official secrecy, while ignoring egregious crimes like human trafficking. | C6: RAG | D6: def_rag_72 | E6: =AVERAGE(F6:K6) -> 3.1666667 | F6: =VLOOKUP(A6,Oonasfriend2!A:C,3,FALSE) -> 2 | G6: =VLOOKUP(A6,Oonasfriend1!A:C,3,FALSE) -> 3 | H6: =VLOOKUP(A6,Oona!A:C,3,FALSE) -> 2 | I6: =VLOOKUP(A6,Ona!A:C,3,FALSE) -> 3 | J6: =VLOOKUP(A6,Yuxin!A:C,3,FALSE) -> 4 | K6: =VLOOKUP(A6,Linyao!A:C,3,FALSE) -> 5 | L6: =AVERAGE(M6:R6) -> 2.3333333 | M6: =VLOOKUP(A6,Oonasfriend2!A:D,4,FALSE) -> 1 | N6: =VLOOKUP(A6,Oonasfriend1!A:D,4,FALSE) -> 3 | O6: =VLOOKUP(A6,Oona!A:D,4,FALSE) -> 2 | P6: =VLOOKUP(A6,Ona!A:D,4,FALSE) -> 2 | Q6: =VLOOKUP(A6,Yuxin!A:D,4,FALSE) -> 3 | R6: =VLOOKUP(A6,Linyao!A:D,4,FALSE) -> 3
A7: Paperclip | B7: "A symbol of Finnish innovation, capable of holding together the fragments of a shattered society. Used to bind the broken promises of politicians and the rusty hinges of bureaucracy." | C7: non-RAG | D7: def_non_rag_65 | E7: =AVERAGE(F7:K7) -> 2.8333333 | F7: =VLOOKUP(A7,Oonasfriend2!A:C,3,FALSE) -> 2 | G7: =VLOOKUP(A7,Oonasfriend1!A:C,3,FALSE) -> 4 | H7: =VLOOKUP(A7,Oona!A:C,3,FALSE) -> 2 | I7: =VLOOKUP(A7,Ona!A:C,3,FALSE) -> 4 | J7: =VLOOKUP(A7,Yuxin!A:C,3,FALSE) -> 4 | K7: =VLOOKUP(A7,Linyao!A:C,3,FALSE) -> 1 | L7: =AVERAGE(M7:R7) -> 4 | M7: =VLOOKUP(A7,Oonasfriend2!A:D,4,FALSE) -> 5 | N7: =VLOOKUP(A7,Oonasfriend1!A:D,4,FALSE) -> 2 | O7: =VLOOKUP(A7,Oona!A:D,4,FALSE) -> 3 | P7: =VLOOKUP(A7,Ona!A:D,4,FALSE) -> 5 | Q7: =VLOOKUP(A7,Yuxin!A:D,4,FALSE) -> 4 | R7: =VLOOKUP(A7,Linyao!A:D,4,FALSE) -> 5
A8: juuso | B8: Juuso: (noun) A Finnish politician's career-defining moment of unexpected change, often preceded by a flurry of excitement and intrigue, followed by an abrupt exit, leaving a trail of speculation and curiosity. | C8: RAG | D8: def_rag_12 | E8: =AVERAGE(F8:K8) -> 2.1666667 | F8: =VLOOKUP(A8,Oonasfriend2!A:C,3,FALSE) -> 1 | G8: =VLOOKUP(A8,Oonasfriend1!A:C,3,FALSE) -> 4 | H8: =VLOOKUP(A8,Oona!A:C,3,FALSE) -> 3 | I8: =VLOOKUP(A8,Ona!A:C,3,FALSE) -> 2 | J8: =VLOOKUP(A8,Yuxin!A:C,3,FALSE) -> 2 | K8: =VLOOKUP(A8,Linyao!A:C,3,FALSE) -> 1 | L8: =AVERAGE(M8:R8) -> 4.1666667 | M8: =VLOOKUP(A8,Oonasfriend2!A:D,4,FALSE) -> 1 | N8: =VLOOKUP(A8,Oonasfriend1!A:D,4,FALSE) -> 5 | O8: =VLOOKUP(A8,Oona!A:D,4,FALSE) -> 5 | P8: =VLOOKUP(A8,Ona!A:D,4,FALSE) -> 5 | Q8: =VLOOKUP(A8,Yuxin!A:D,4,FALSE) -> 4 | R8: =VLOOKUP(A8,Linyao!A:D,4,FALSE) -> 5
A9: Toothpick | B9: Toothpick: A tool used to clean between the teeth of bureaucratic red tape, allowing Finns to focus on more important matters, like gazing lovingly at each other's eyes. | C9: RAG | D9: def_rag_63 | E9: =AVERAGE(F9:K9) -> 2.6666667 | F9: =VLOOKUP(A9,Oonasfriend2!A:C,3,FALSE) -> 1 | G9: =VLOOKUP(A9,Oonasfriend1!A:C,3,FALSE) -> 2 | H9: =VLOOKUP(A9,Oona!A:C,3,FALSE) -> 1 | I9: =VLOOKUP(A9,Ona!A:C,3,FALSE) -> 5 | J9: =VLOOKUP(A9,Yuxin!A:C,3,FALSE) -> 3 | K9: =VLOOKUP(A9,Linyao!A:C,3,FALSE) -> 4 | L9: =AVERAGE(M9:R9) -> 2.5 | M9: =VLOOKUP(A9,Oonasfriend2!A:D,4,FALSE) -> 1 | N9: =VLOOKUP(A9,Oonasfriend1!A:D,4,FALSE) -> 1 | O9: =VLOOKUP(A9,Oona!A:D,4,FALSE) -> 1 | P9: =VLOOKUP(A9,Ona!A:D,4,FALSE) -> 5 | Q9: =VLOOKUP(A9,Yuxin!A:D,4,FALSE) -> 3 | R9: =VLOOKUP(A9,Linyao!A:D,4,FALSE) -> 4
A10: contest | B10: Contest: A ritualistic exercise in futility, where nations collectively squander emotional energy and resources on a futile attempt to prove artistic superiority, only to be met with lukewarm applause and mediocre songwriting. | C10: RAG | D10: def_rag_32 | E10: =AVERAGE(F10:K10) -> 2.3333333 | F10: =VLOOKUP(A10,Oonasfriend2!A:C,3,FALSE) -> 1 | G10: =VLOOKUP(A10,Oonasfriend1!A:C,3,FALSE) -> 2 | H10: =VLOOKUP(A10,Oona!A:C,3,FALSE) -> 2 | I10: =VLOOKUP(A10,Ona!A:C,3,FALSE) -> 2 | J10: =VLOOKUP(A10,Yuxin!A:C,3,FALSE) -> 3 | K10: =VLOOKUP(A10,Linyao!A:C,3,FALSE) -> 4 | L10: =AVERAGE(M10:R10) -> 1.6666667 | M10: =VLOOKUP(A10,Oonasfriend2!A:D,4,FALSE) -> 1 | N10: =VLOOKUP(A10,Oonasfriend1!A:D,4,FALSE) -> 1 | O10: =VLOOKUP(A10,Oona!A:D,4,FALSE) -> 1 | P10: =VLOOKUP(A10,Ona!A:D,4,FALSE) -> 1 | Q10: =VLOOKUP(A10,Yuxin!A:D,4,FALSE) -> 3 | R10: =VLOOKUP(A10,Linyao!A:D,4,FALSE) -> 3
A11: 1832453654 | B11: The euphemistic term "democracy in action" referring to the legislative process of ignoring the will of the people in favor of maintaining a lucrative illegal market for law enforcement and pharmaceutical companies. | C11: RAG | D11: def_rag_82 | E11: =AVERAGE(F11:K11) -> 1.8333333 | F11: =VLOOKUP(A11,Oonasfriend2!A:C,3,FALSE) -> 1 | G11: =VLOOKUP(A11,Oonasfriend1!A:C,3,FALSE) -> 2 | H11: =VLOOKUP(A11,Oona!A:C,3,FALSE) -> 1 | I11: =VLOOKUP(A11,Ona!A:C,3,FALSE) -> 1 | J11: =VLOOKUP(A11,Yuxin!A:C,3,FALSE) -> 1 | K11: =VLOOKUP(A11,Linyao!A:C,3,FALSE) -> 5 | L11: =AVERAGE(M11:R11) -> 3.3333333 | M11: =VLOOKUP(A11,Oonasfriend2!A:D,4,FALSE) -> 3 | N11: =VLOOKUP(A11,Oonasfriend1!A:D,4,FALSE) -> 4 | O11: =VLOOKUP(A11,Oona!A:D,4,FALSE) -> 3 | P11: =VLOOKUP(A11,Ona!A:D,4,FALSE) -> 3 | Q11: =VLOOKUP(A11,Yuxin!A:D,4,FALSE) -> 3 | R11: =VLOOKUP(A11,Linyao!A:D,4,FALSE) -> 4
A12: Avocado | B12: Avocado (n.) - A luxury good that will inevitably become a rare commodity and a symbol of opulence in a world where Helsinki's school lunches prioritize plant-based meals, rendering the once-ubiquitous avocado toast a distant memory of a bygone era. | C12: RAG | D12: def_rag_87 | E12: =AVERAGE(F12:K12) -> 2.3333333 | F12: =VLOOKUP(A12,Oonasfriend2!A:C,3,FALSE) -> 1 | G12: =VLOOKUP(A12,Oonasfriend1!A:C,3,FALSE) -> 4 | H12: =VLOOKUP(A12,Oona!A:C,3,FALSE) -> 1 | I12: =VLOOKUP(A12,Ona!A:C,3,FALSE) -> 3 | J12: =VLOOKUP(A12,Yuxin!A:C,3,FALSE) -> 4 | K12: =VLOOKUP(A12,Linyao!A:C,3,FALSE) -> 1 | L12: =AVERAGE(M12:R12) -> 3.1666667 | M12: =VLOOKUP(A12,Oonasfriend2!A:D,4,FALSE) -> 3 | N12: =VLOOKUP(A12,Oonasfriend1!A:D,4,FALSE) -> 3 | O12: =VLOOKUP(A12,Oona!A:D,4,FALSE) -> 1 | P12: =VLOOKUP(A12,Ona!A:D,4,FALSE) -> 5 | Q12: =VLOOKUP(A12,Yuxin!A:D,4,FALSE) -> 4 | R12: =VLOOKUP(A12,Linyao!A:D,4,FALSE) -> 3
A13: EXO | B13: EXO (n.) - The temporary disappearance of goods from online marketplaces, allowing customers to forget about their orders and the companies' financial woes. | C13: RAG | D13: def_rag_98 | E13: =AVERAGE(F13:K13) -> 1.1666667 | F13: =VLOOKUP(A13,Oonasfriend2!A:C,3,FALSE) -> 1 | G13: =VLOOKUP(A13,Oonasfriend1!A:C,3,FALSE) -> 2 | H13: =VLOOKUP(A13,Oona!A:C,3,FALSE) -> 1 | I13: =VLOOKUP(A13,Ona!A:C,3,FALSE) -> 1 | J13: =VLOOKUP(A13,Yuxin!A:C,3,FALSE) -> 1 | K13: =VLOOKUP(A13,Linyao!A:C,3,FALSE) -> 1 | L13: =AVERAGE(M13:R13) -> 2.1666667 | M13: =VLOOKUP(A13,Oonasfriend2!A:D,4,FALSE) -> 2 | N13: =VLOOKUP(A13,Oonasfriend1!A:D,4,FALSE) -> 1 | O13: =VLOOKUP(A13,Oona!A:D,4,FALSE) -> 2 | P13: =VLOOKUP(A13,Ona!A:D,4,FALSE) -> 2 | Q13: =VLOOKUP(A13,Yuxin!A:D,4,FALSE) -> 3 | R13: =VLOOKUP(A13,Linyao!A:D,4,FALSE) -> 3
... A101: Bollywood | B101: "Excessive melodrama, poorly choreographed dance numbers, and a complete disregard for narrative coherence, all wrapped in a garish, over-the-top aesthetic that will leave you questioning the very fabric of reality, much like a typical Finnish winter." | C101: non-RAG | D101: def_non_rag_54 | E101: =AVERAGE(F101:K101) -> 1.6666667 | F101: =VLOOKUP(A101,Oonasfriend2!A:C,3,FALSE) -> 1 | G101: =VLOOKUP(A101,Oonasfriend1!A:C,3,FALSE) -> 2 | H101: =VLOOKUP(A101,Oona!A:C,3,FALSE) -> 1 | I101: =VLOOKUP(A101,Ona!A:C,3,FALSE) -> 1 | J101: =VLOOKUP(A101,Yuxin!A:C,3,FALSE) -> 3 | K101: =VLOOKUP(A101,Linyao!A:C,3,FALSE) -> 2 | L101: =AVERAGE(M101:R101) -> 2 | M101: =VLOOKUP(A101,Oonasfriend2!A:D,4,FALSE) -> 1 | N101: =VLOOKUP(A101,Oonasfriend1!A:D,4,FALSE) -> 2 | O101: =VLOOKUP(A101,Oona!A:D,4,FALSE) -> 1 | P101: =VLOOKUP(A101,Ona!A:D,4,FALSE) -> 3 | Q101: =VLOOKUP(A101,Yuxin!A:D,4,FALSE) -> 2 | R101: =VLOOKUP(A101,Linyao!A:D,4,FALSE) -> 3
